omnidaemon/__init__.py
omnidaemon/schemas.py
omnidaemon/sdk.py
omnidaemon/agent_runner/README.md
omnidaemon/agent_runner/__init__.py
omnidaemon/agent_runner/agent_supervisor.py
omnidaemon/agent_runner/agent_supervisor_runner.py
omnidaemon/agent_runner/dependency_manager.py
omnidaemon/agent_runner/exceptions.py
omnidaemon/agent_runner/module_discovery.py
omnidaemon/agent_runner/python_callback_adapter.py
omnidaemon/agent_runner/runner.py
omnidaemon/agent_runner/supervisor_storage.py
omnidaemon/agent_runner/types.py
omnidaemon/agent_runner/utils.py
omnidaemon/api/__init__.py
omnidaemon/api/server.py
omnidaemon/cli/__init__.py
omnidaemon/cli/main.py
omnidaemon/event_bus/__init__.py
omnidaemon/event_bus/base.py
omnidaemon/event_bus/redis_stream_bus.py
omnidaemon/storage/__init__.py
omnidaemon/storage/base.py
omnidaemon/storage/json_store.py
omnidaemon/storage/redis_store.py
omnidaemon-0.1.1.dist-info/METADATA
omnidaemon-0.1.1.dist-info/WHEEL
omnidaemon-0.1.1.dist-info/entry_points.txt
omnidaemon-0.1.1.dist-info/licenses/LICENSE
omnidaemon-0.1.1.dist-info/RECORD
