Metadata-Version: 2.4
Name: omnidaemon
Version: 0.1.1
Summary: Universal Event-Driven Runtime Engine for AI Agents
Project-URL: Homepage, https://github.com/omnirexflora-labs/OmniDaemon
Project-URL: Repository, https://github.com/omnirexflora-labs/OmniDaemon
Project-URL: Documentation, https://docs-omnidaemon.omnirexfloralabs.com/docs
Project-URL: Issues, https://github.com/omnirexflora-labs/OmniDaemon/issues
Project-URL: Changelog, https://github.com/omnirexflora-labs/OmniDaemon/releases
Author-email: Abiola Adeshina <abiolaadedayo1993@gmail.com>
License: MIT
License-File: LICENSE
Keywords: agent,ai,automation,background-tasks,event-driven,kafka,microservices,redis-streams,runtime
Classifier: Development Status :: 4 - Beta
Classifier: Intended Audience :: Developers
Classifier: License :: OSI Approved :: MIT License
Classifier: Programming Language :: Python :: 3
Classifier: Programming Language :: Python :: 3.10
Classifier: Programming Language :: Python :: 3.11
Classifier: Programming Language :: Python :: 3.12
Classifier: Programming Language :: Python :: 3.13
Classifier: Topic :: Software Development :: Libraries :: Application Frameworks
Classifier: Topic :: System :: Distributed Computing
Requires-Python: >=3.10
Requires-Dist: aiohttp>=3.9.0
Requires-Dist: fastapi>=0.100.0
Requires-Dist: pip>=25.3
Requires-Dist: psutil>=7.1.3
Requires-Dist: pydantic>=2.0.0
Requires-Dist: python-decouple>=3.8
Requires-Dist: redis>=5.0.0
Requires-Dist: rich>=13.0.0
Requires-Dist: typer>=0.9.0
Requires-Dist: uvicorn>=0.23.0
